azure/mgmt/workloads/__init__.py
azure/mgmt/workloads/_configuration.py
azure/mgmt/workloads/_patch.py
azure/mgmt/workloads/_serialization.py
azure/mgmt/workloads/_vendor.py
azure/mgmt/workloads/_version.py
azure/mgmt/workloads/_workloads_mgmt_client.py
azure/mgmt/workloads/py.typed
azure/mgmt/workloads/aio/__init__.py
azure/mgmt/workloads/aio/_configuration.py
azure/mgmt/workloads/aio/_patch.py
azure/mgmt/workloads/aio/_vendor.py
azure/mgmt/workloads/aio/_workloads_mgmt_client.py
azure/mgmt/workloads/aio/operations/__init__.py
azure/mgmt/workloads/aio/operations/_monitors_operations.py
azure/mgmt/workloads/aio/operations/_operations.py
azure/mgmt/workloads/aio/operations/_patch.py
azure/mgmt/workloads/aio/operations/_provider_instances_operations.py
azure/mgmt/workloads/aio/operations/_sap_application_server_instances_operations.py
azure/mgmt/workloads/aio/operations/_sap_central_instances_operations.py
azure/mgmt/workloads/aio/operations/_sap_database_instances_operations.py
azure/mgmt/workloads/aio/operations/_sap_landscape_monitor_operations.py
azure/mgmt/workloads/aio/operations/_sap_virtual_instances_operations.py
azure/mgmt/workloads/aio/operations/_workloads_mgmt_client_operations.py
azure/mgmt/workloads/models/__init__.py
azure/mgmt/workloads/models/_models_py3.py
azure/mgmt/workloads/models/_patch.py
azure/mgmt/workloads/models/_workloads_mgmt_client_enums.py
azure/mgmt/workloads/operations/__init__.py
azure/mgmt/workloads/operations/_monitors_operations.py
azure/mgmt/workloads/operations/_operations.py
azure/mgmt/workloads/operations/_patch.py
azure/mgmt/workloads/operations/_provider_instances_operations.py
azure/mgmt/workloads/operations/_sap_application_server_instances_operations.py
azure/mgmt/workloads/operations/_sap_central_instances_operations.py
azure/mgmt/workloads/operations/_sap_database_instances_operations.py
azure/mgmt/workloads/operations/_sap_landscape_monitor_operations.py
azure_mgmt_workloads-1.0.0.dist-info/LICENSE
azure_mgmt_workloads-1.0.0.dist-info/METADATA
azure_mgmt_workloads-1.0.0.dist-info/WHEEL
azure_mgmt_workloads-1.0.0.dist-info/top_level.txt
azure_mgmt_workloads-1.0.0.dist-info/RECORD
